{
   "dashboards": [{
      "autoswitchEnabled": false,
      "columnCount": 1,
      "columnProportion": "1",
      "creationTime": 1556649851598,
      "dashboardNavigations": {},
      "description": "",
      "disabled": false,
      "gridsterMaxColumns": 12,
      "hidden": false,
      "homeTab": false,
      "id": "355a75be-e2ac-4916-8e10-02d87423d7d2",
      "importAttempts": 0,
      "importComplete": true,
      "isDefault": false,
      "locked": false,
      "name": "Custom Dashboards/Troubleshooting MSSQL Instances",
      "namePath": "Custom Dashboards",
      "rank": 465,
      "shared": false,
      "states": [],
      "temporary": false,
      "userId": "2a41f813-7a96-4cf0-ace6-e8c383b25024",
      "widgetInteractions": [
         {
            "type": "resourceId",
            "widgetIdProvider": "9b427206-31fd-412b-8f52-5af8ea7dc97e",
            "widgetIdReceiver": "e654c985-72e1-4176-aa12-b639d70093ad"
         },
         {
            "type": "resourceId",
            "widgetIdProvider": "9b427206-31fd-412b-8f52-5af8ea7dc97e",
            "widgetIdReceiver": "7b480a80-cf20-4be4-be45-884f5d1e3a07"
         },
         {
            "type": "resourceId",
            "widgetIdProvider": "7b480a80-cf20-4be4-be45-884f5d1e3a07",
            "widgetIdReceiver": "9699b968-3e07-404d-8f3b-600249fc1712"
         },
         {
            "type": "resourceId",
            "widgetIdProvider": "9b427206-31fd-412b-8f52-5af8ea7dc97e",
            "widgetIdReceiver": "524c13da-6de8-4079-b392-30b373401f93"
         },
         {
            "type": "resourceId",
            "widgetIdProvider": "9b427206-31fd-412b-8f52-5af8ea7dc97e",
            "widgetIdReceiver": "486c7db0-59fd-4e81-ae5f-12ebcf92ee6e"
         },
         {
            "type": "resourceId",
            "widgetIdProvider": "524c13da-6de8-4079-b392-30b373401f93",
            "widgetIdReceiver": "78b3bdc0-5dac-41e3-8520-a520db96e873"
         }
      ],
      "widgets": [
         {
            "collapsed": false,
            "config": {
               "additionalColumns": [{
                  "boxLabel": "SQL Version",
                  "metricKey": "general|sql_version",
                  "metricName": "General|SQL Version",
                  "resourceKindId": "resourceKind:id:0_::_"
               }],
               "mode": 0,
               "refreshContent": {"refreshContent": true},
               "refreshInterval": 300,
               "selectFirstRow": {"selectFirstRow": false},
               "tagFilter": {
                  "path": ["/source/kind/kind:resourceKind:id:0_::_"],
                  "value": {
                     "adapterInstance": [],
                     "adapterKind": [],
                     "bus": [],
                     "collector": [],
                     "day": [],
                     "exclaim": false,
                     "healthRange": [],
                     "kind": ["resourceKind:id:0_::_"],
                     "maintenanceSchedule": [],
                     "state": [],
                     "status": [],
                     "tag": [],
                     "tier": []
                  }
               },
               "title": "1.  Select MSSQL Instance"
            },
            "gridsterCoords": {
               "h": 5,
               "w": 3,
               "x": 1,
               "y": 1
            },
            "height": 267,
            "id": "9b427206-31fd-412b-8f52-5af8ea7dc97e",
            "states": [{
               "key": "permResGrid_widget_355a75be-e2ac-4916-8e10-02d87423d7d2_9b427206-31fd-412b-8f52-5af8ea7dc97e",
               "value": "o%3Acolumns%3Da%253Ao%25253Aid%25253Ds%2525253Ah1%25255Ehidden%25253Db%2525253A1%25255Ewidth%25253Dn%2525253A100%255Eo%25253Aid%25253Ds%2525253Ah2%25255Ewidth%25253Dn%2525253A221%255Eo%25253Aid%25253Ds%2525253Ah3%25255Ehidden%25253Db%2525253A1%25255Ewidth%25253Dn%2525253A100%255Eo%25253Aid%25253Ds%2525253Ah4%25255Ehidden%25253Db%2525253A1%255Eo%25253Aid%25253Ds%2525253Ah5%25255Ehidden%25253Db%2525253A1%25255Ewidth%25253Dn%2525253A234%255Eo%25253Aid%25253Ds%2525253Ah6%25255Ehidden%25253Db%2525253A1%255Eo%25253Aid%25253Ds%2525253Ah7%25255Ehidden%25253Db%2525253A1%25255Ewidth%25253Dn%2525253A100%255Eo%25253Aid%25253Ds%2525253Ah8%25255Ehidden%25253Db%2525253A1%25255Ewidth%25253Dn%2525253A100%255Eo%25253Aid%25253Ds%2525253Ah9%25255Ehidden%25253Db%2525253A1%25255Ewidth%25253Dn%2525253A100%255Eo%25253Aid%25253Ds%2525253Ah10%25255Ehidden%25253Db%2525253A1%25255Ewidth%25253Dn%2525253A100%255Eo%25253Aid%25253Ds%2525253Ah11%25255Ehidden%25253Db%2525253A1%25255Ewidth%25253Dn%2525253A100%255Eo%25253Aid%25253Ds%2525253Ah12%25255Ehidden%25253Db%2525253A1%25255Ewidth%25253Dn%2525253A100%255Eo%25253Aid%25253Ds%2525253Ah13%25255Ehidden%25253Db%2525253A1%25255Ewidth%25253Dn%2525253A100%255Eo%25253Aid%25253Ds%2525253Ah17%25255Ehidden%25253Db%2525253A0%25255Ewidth%25253Dn%2525253A332%255Eo%25253Aid%25253Ds%2525253Ah14%25255Ehidden%25253Db%2525253A0%255Eo%25253Aid%25253Ds%2525253Ah15%25255Ehidden%25253Db%2525253A0%255Eo%25253Aid%25253Ds%2525253Ah16%25255Ehidden%25253Db%2525253A1%25255Ewidth%25253Dn%2525253A100%255Eo%25253Aid%25253Ds%2525253Ah18%25255Ehidden%25253Db%2525253A1%25255Ewidth%25253Dn%2525253A100%255Eo%25253Aid%25253Ds%2525253Ah19%25255Ehidden%25253Db%2525253A1%25255Ewidth%25253Dn%2525253A100%255Eo%25253Aid%25253Ds%2525253Ah20%25255Ehidden%25253Db%2525253A1%25255Ewidth%25253Dn%2525253A100%255Eo%25253Aid%25253Ds%2525253Ah21%25255Ehidden%25253Db%2525253A1%25255Ewidth%25253Dn%2525253A100%255Eo%25253Aid%25253Ds%2525253Ah22%25255Ehidden%25253Db%2525253A1%25255Ewidth%25253Dn%2525253A100%255Eo%25253Aid%25253Ds%2525253Ah23%25255Ehidden%25253Db%2525253A1%25255Ewidth%25253Dn%2525253A100%255Eo%25253Aid%25253Ds%2525253Ah24%25255Ehidden%25253Db%2525253A1%25255Ewidth%25253Dn%2525253A100%255Eo%25253Aid%25253Ds%2525253Ah25%25255Ehidden%25253Db%2525253A1%25255Ewidth%25253Dn%2525253A100%255Eo%25253Aid%25253Ds%2525253Ah26%25255Ehidden%25253Db%2525253A1%25255Ewidth%25253Dn%2525253A100%255Eo%25253Aid%25253Ds%2525253Ah27%25255Ehidden%25253Db%2525253A1%25255Ewidth%25253Dn%2525253A100%255Eo%25253Aid%25253Ds%2525253Ah28%25255Ehidden%25253Db%2525253A1%25255Ewidth%25253Dn%2525253A100%255Eo%25253Aid%25253Ds%2525253Ah29%25255Ehidden%25253Db%2525253A1%25255Ewidth%25253Dn%2525253A100%255Eo%25253Aid%25253Ds%2525253Ah30%25255Ehidden%25253Db%2525253A1%25255Ewidth%25253Dn%2525253A100%255Eo%25253Aid%25253Ds%2525253Ah31%25255Ehidden%25253Db%2525253A1%25255Ewidth%25253Dn%2525253A100%255Eo%25253Aid%25253Ds%2525253Ah32%25255Ehidden%25253Db%2525253A1%25255Ewidth%25253Dn%2525253A100%255Eo%25253Aid%25253Ds%2525253Ah33%25255Ehidden%25253Db%2525253A1%25255Ewidth%25253Dn%2525253A100%255Eo%25253Aid%25253Ds%2525253Ah34%25255Ehidden%25253Db%2525253A1%25255Ewidth%25253Dn%2525253A100%255Eo%25253Aid%25253Ds%2525253Ah35%25255Ehidden%25253Db%2525253A1%25255Ewidth%25253Dn%2525253A100%255Eo%25253Aid%25253Ds%2525253Ah36%25255Ehidden%25253Db%2525253A1%25255Ewidth%25253Dn%2525253A100%255Eo%25253Aid%25253Ds%2525253Ah37%25255Ehidden%25253Db%2525253A1%25255Ewidth%25253Dn%2525253A100%255Eo%25253Aid%25253Ds%2525253Ah38%25255Ehidden%25253Db%2525253A1%25255Ewidth%25253Dn%2525253A100%255Eo%25253Aid%25253Ds%2525253Ah39%25255Ehidden%25253Db%2525253A1%25255Ewidth%25253Dn%2525253A100%255Eo%25253Aid%25253Ds%2525253Ah40%25255Ehidden%25253Db%2525253A1%25255Ewidth%25253Dn%2525253A100%255Eo%25253Aid%25253Ds%2525253Ah41%25255Ehidden%25253Db%2525253A1%25255Ewidth%25253Dn%2525253A100%255Eo%25253Aid%25253Ds%2525253Ah42%25255Ehidden%25253Db%2525253A1%25255Ewidth%25253Dn%2525253A100%255Eo%25253Aid%25253Ds%2525253Ah43%25255Ehidden%25253Db%2525253A1%25255Ewidth%25253Dn%2525253A100%255Eo%25253Aid%25253Ds%2525253Ah44%25255Ehidden%25253Db%2525253A1%25255Ewidth%25253Dn%2525253A100%255Eo%25253Aid%25253Ds%2525253Ah45%25255Ehidden%25253Db%2525253A1%25255Ewidth%25253Dn%2525253A100%255Eo%25253Aid%25253Ds%2525253Ah46%25255Ehidden%25253Db%2525253A1%25255Ewidth%25253Dn%2525253A100"
            }],
            "title": "1.  Select MSSQL Instance",
            "type": "ResourceList"
         },
         {
            "collapsed": false,
            "config": {
               "boxColumns": 5,
               "boxHeight": null,
               "customFilter": {
                  "excludedResources": null,
                  "filter": [],
                  "includedResources": null
               },
               "depth": 1,
               "labelSize": 12,
               "maxCellCount": 100,
               "metric": {
                  "mode": "resourceKind",
                  "resourceKindMetrics": [
                     {
                        "colorMethod": 1,
                        "id": "extModel9212-1",
                        "isStringMetric": false,
                        "metricKey": "connection_capacity|number_of_active_connections",
                        "metricName": "Connection Capacity|Active Connections",
                        "metricUnitId": -1,
                        "resourceKindId": "resourceKind:id:0_::_",
                        "resourceKindName": "Microsoft SQL Server Instance",
                        "unit": "Auto"
                     },
                     {
                        "colorMethod": 1,
                        "id": "extModel9212-2",
                        "isStringMetric": false,
                        "metricKey": "connection_capacity|number_of_connections",
                        "metricName": "Connection Capacity|Connections",
                        "metricUnitId": -1,
                        "resourceKindId": "resourceKind:id:0_::_",
                        "resourceKindName": "Microsoft SQL Server Instance",
                        "unit": "Auto"
                     },
                     {
                        "colorMethod": 1,
                        "id": "extModel9212-3",
                        "isStringMetric": false,
                        "metricKey": "jobs|number_of_failed_jobs",
                        "metricName": "Jobs|Failed Jobs",
                        "metricUnitId": null,
                        "resourceKindId": "resourceKind:id:0_::_",
                        "resourceKindName": "Microsoft SQL Server Instance",
                        "unit": null
                     },
                     {
                        "colorMethod": 1,
                        "id": "extModel9212-4",
                        "isStringMetric": false,
                        "metricKey": "locks|deadlock",
                        "metricName": "Locks|Deadlocks",
                        "metricUnitId": null,
                        "resourceKindId": "resourceKind:id:0_::_",
                        "resourceKindName": "Microsoft SQL Server Instance",
                        "unit": null
                     },
                     {
                        "colorMethod": 1,
                        "id": "extModel9212-5",
                        "isStringMetric": false,
                        "metricKey": "locks|lock_request",
                        "metricName": "Locks|Lock Requests",
                        "metricUnitId": null,
                        "resourceKindId": "resourceKind:id:0_::_",
                        "resourceKindName": "Microsoft SQL Server Instance",
                        "unit": null
                     },
                     {
                        "colorMethod": 1,
                        "id": "extModel9926-1",
                        "isStringMetric": false,
                        "metricKey": "queries|queries_end_in_deadlocks",
                        "metricName": "Queries|Dead Locked Queries",
                        "metricUnitId": null,
                        "resourceKindId": "resourceKind:id:0_::_",
                        "resourceKindName": "Microsoft SQL Server Instance",
                        "unit": null
                     },
                     {
                        "colorMethod": 1,
                        "id": "extModel18236-1",
                        "isStringMetric": false,
                        "metricKey": "disk_access|iops",
                        "metricName": "Disk Access|IOPS",
                        "metricUnitId": -1,
                        "resourceKindId": "resourceKind:id:0_::_",
                        "resourceKindName": "Microsoft SQL Server Instance",
                        "unit": "Auto"
                     },
                     {
                        "colorMethod": 1,
                        "id": "extModel18236-2",
                        "isStringMetric": false,
                        "metricKey": "general|max_thread_count",
                        "metricName": "General|Max Thread Count",
                        "metricUnitId": null,
                        "resourceKindId": "resourceKind:id:0_::_",
                        "resourceKindName": "Microsoft SQL Server Instance",
                        "unit": null
                     },
                     {
                        "colorMethod": 1,
                        "id": "extModel18753-1",
                        "isStringMetric": false,
                        "metricKey": "database_performance|log_cache_hit_ratio",
                        "metricName": "Database Performance|Log Cache Hit Ratio",
                        "metricUnitId": null,
                        "resourceKindId": "resourceKind:id:0_::_",
                        "resourceKindName": "Microsoft SQL Server Instance",
                        "unit": null
                     },
                     {
                        "colorMethod": 1,
                        "id": "extModel16496-1",
                        "isStringMetric": false,
                        "link": "",
                        "metricKey": "buffer|buffer_cache_hit_ratio",
                        "metricName": "Buffer|Buffer Cache Hit Ratio",
                        "metricUnitId": null,
                        "orangeBound": null,
                        "redBound": null,
                        "resourceKindId": "resourceKind:id:0_::_",
                        "resourceKindName": "Microsoft SQL Server Instance",
                        "unit": null,
                        "yellowBound": null
                     },
                     {
                        "colorMethod": 1,
                        "id": "extModel16496-2",
                        "isStringMetric": false,
                        "link": "",
                        "metricKey": "cpu|cpu_usage",
                        "metricName": "CPU|CPU Usage",
                        "metricUnitId": -1,
                        "orangeBound": null,
                        "redBound": null,
                        "resourceKindId": "resourceKind:id:0_::_",
                        "resourceKindName": "Microsoft SQL Server Instance",
                        "unit": "Auto",
                        "yellowBound": null
                     },
                     {
                        "colorMethod": 1,
                        "id": "extModel16496-3",
                        "isStringMetric": false,
                        "link": "",
                        "metricKey": "database_performance|transactions",
                        "metricName": "Database Performance|Transactions",
                        "metricUnitId": null,
                        "orangeBound": null,
                        "redBound": null,
                        "resourceKindId": "resourceKind:id:0_::_",
                        "resourceKindName": "Microsoft SQL Server Instance",
                        "unit": null,
                        "yellowBound": null
                     },
                     {
                        "colorMethod": 1,
                        "id": "extModel16496-4",
                        "isStringMetric": false,
                        "link": "",
                        "metricKey": "disk_access|read_ops",
                        "metricName": "Disk Access|Read Operations",
                        "metricUnitId": -1,
                        "orangeBound": null,
                        "redBound": null,
                        "resourceKindId": "resourceKind:id:0_::_",
                        "resourceKindName": "Microsoft SQL Server Instance",
                        "unit": "Auto",
                        "yellowBound": null
                     },
                     {
                        "colorMethod": 1,
                        "id": "extModel16496-5",
                        "isStringMetric": false,
                        "link": "",
                        "metricKey": "disk_access|write_ops",
                        "metricName": "Disk Access|Write Operations",
                        "metricUnitId": -1,
                        "orangeBound": null,
                        "redBound": null,
                        "resourceKindId": "resourceKind:id:0_::_",
                        "resourceKindName": "Microsoft SQL Server Instance",
                        "unit": "Auto",
                        "yellowBound": null
                     },
                     {
                        "colorMethod": 1,
                        "id": "extModel16496-6",
                        "isStringMetric": false,
                        "link": "",
                        "metricKey": "memory|memory_usage",
                        "metricName": "Memory|Memory Usage",
                        "metricUnitId": -1,
                        "orangeBound": null,
                        "redBound": null,
                        "resourceKindId": "resourceKind:id:0_::_",
                        "resourceKindName": "Microsoft SQL Server Instance",
                        "unit": "Auto",
                        "yellowBound": null
                     }
                  ],
                  "resourceMetrics": [],
                  "subMode": "resourceKindAll"
               },
               "mode": {"layoutMode": "fixedView"},
               "oldMetricValues": false,
               "periodLength": "last7Days",
               "refreshContent": {"refreshContent": true},
               "refreshInterval": 300,
               "relationshipMode": {"relationshipMode": 0},
               "resInteractionMode": null,
               "resource": [],
               "roundDecimals": null,
               "selfProvider": {"selfProvider": false},
               "showDT": {"showDT": false},
               "showMetricName": {"showMetricName": true},
               "showMetricUnit": {"showMetricUnit": false},
               "showResourceName": {"showResourceName": false},
               "showSparkline": {"showSparkline": false},
               "title": "2.  What does the selected MSSQL Instance scorecard look like?",
               "valueSize": 24,
               "visualTheme": 5
            },
            "gridsterCoords": {
               "h": 5,
               "w": 9,
               "x": 4,
               "y": 1
            },
            "height": 267,
            "id": "e654c985-72e1-4176-aa12-b639d70093ad",
            "title": "2.  What does the selected MSSQL Instance scorecard look like?",
            "type": "Scoreboard"
         },
         {
            "collapsed": false,
            "config": {
               "additionalColumns": [
                  {
                     "boxLabel": "Instance Parents",
                     "metricKey": "relationships|SqlServer_parent",
                     "metricName": "Relationships|Instance Parents",
                     "resourceKindId": "resourceKind:id:1_::_"
                  },
                  {
                     "boxLabel": "Status",
                     "metricKey": "general|status",
                     "metricName": "General|Status",
                     "resourceKindId": "resourceKind:id:1_::_"
                  },
                  {
                     "boxLabel": "Time Since Creation (days)",
                     "metricKey": "general|time_since_creation",
                     "metricName": "General|Time Since Creation (d)",
                     "resourceKindId": "resourceKind:id:1_::_"
                  },
                  {
                     "boxLabel": "DB Log Size (MB)",
                     "metricKey": "size|db_log_size",
                     "metricName": "Size|Database Log Size (MiB)",
                     "resourceKindId": "resourceKind:id:1_::_"
                  },
                  {
                     "boxLabel": "DB Row Size (MB)",
                     "metricKey": "size|db_row_size",
                     "metricName": "Size|Database Row Size (MiB)",
                     "resourceKindId": "resourceKind:id:1_::_"
                  },
                  {
                     "boxLabel": "Total Used Disk Size (MB)",
                     "metricKey": "size|db_total_size",
                     "metricName": "Size|Total Used Disk Size (MiB)",
                     "resourceKindId": "resourceKind:id:1_::_"
                  }
               ],
               "mode": -1,
               "refreshContent": {"refreshContent": true},
               "refreshInterval": 300,
               "selectFirstRow": {"selectFirstRow": false},
               "tagFilter": {
                  "path": ["/source/kind/kind:resourceKind:id:1_::_"],
                  "value": {
                     "adapterInstance": [],
                     "adapterKind": [],
                     "bus": [],
                     "collector": [],
                     "day": [],
                     "exclaim": false,
                     "healthRange": [],
                     "kind": ["resourceKind:id:1_::_"],
                     "maintenanceSchedule": [],
                     "state": [],
                     "status": [],
                     "tag": [],
                     "tier": []
                  }
               },
               "title": "4.  What MSSQL Databases are in the selected Instance?"
            },
            "gridsterCoords": {
               "h": 5,
               "w": 6,
               "x": 1,
               "y": 12
            },
            "height": 267,
            "id": "7b480a80-cf20-4be4-be45-884f5d1e3a07",
            "states": [{
               "key": "permResGrid_widget_355a75be-e2ac-4916-8e10-02d87423d7d2_7b480a80-cf20-4be4-be45-884f5d1e3a07",
               "value": "o%3Acolumns%3Da%253Ao%25253Aid%25253Ds%2525253Ah1%25255Ehidden%25253Db%2525253A1%25255Ewidth%25253Dn%2525253A100%255Eo%25253Aid%25253Ds%2525253Ah2%25255Ewidth%25253Dn%2525253A177.611328125%255Eo%25253Aid%25253Ds%2525253Ah3%25255Ehidden%25253Db%2525253A1%25255Ewidth%25253Dn%2525253A100%255Eo%25253Aid%25253Ds%2525253Ah4%25255Ehidden%25253Db%2525253A1%255Eo%25253Aid%25253Ds%2525253Ah5%25255Ehidden%25253Db%2525253A1%25255Ewidth%25253Dn%2525253A236%255Eo%25253Aid%25253Ds%2525253Ah6%25255Ehidden%25253Db%2525253A1%255Eo%25253Aid%25253Ds%2525253Ah7%25255Ehidden%25253Db%2525253A1%25255Ewidth%25253Dn%2525253A100%255Eo%25253Aid%25253Ds%2525253Ah8%25255Ehidden%25253Db%2525253A1%25255Ewidth%25253Dn%2525253A100%255Eo%25253Aid%25253Ds%2525253Ah9%25255Ehidden%25253Db%2525253A1%25255Ewidth%25253Dn%2525253A100%255Eo%25253Aid%25253Ds%2525253Ah10%25255Ehidden%25253Db%2525253A1%25255Ewidth%25253Dn%2525253A100%255Eo%25253Aid%25253Ds%2525253Ah11%25255Ehidden%25253Db%2525253A1%25255Ewidth%25253Dn%2525253A100%255Eo%25253Aid%25253Ds%2525253Ah12%25255Ehidden%25253Db%2525253A1%25255Ewidth%25253Dn%2525253A100%255Eo%25253Aid%25253Ds%2525253Ah13%25255Ehidden%25253Db%2525253A1%25255Ewidth%25253Dn%2525253A100%255Eo%25253Aid%25253Ds%2525253Ah14%25255Ehidden%25253Db%2525253A1%255Eo%25253Aid%25253Ds%2525253Ah15%25255Ehidden%25253Db%2525253A1%255Eo%25253Aid%25253Ds%2525253Ah16%25255Ehidden%25253Db%2525253A1%25255Ewidth%25253Dn%2525253A100%255Eo%25253Aid%25253Ds%2525253Ah18%25255Ehidden%25253Db%2525253A0%25255Ewidth%25253Dn%2525253A76%255Eo%25253Aid%25253Ds%2525253Ah17%25255Ehidden%25253Db%2525253A0%25255Ewidth%25253Dn%2525253A226.576171875%255Eo%25253Aid%25253Ds%2525253Ah19%25255Ehidden%25253Db%2525253A0%25255Ewidth%25253Dn%2525253A192.798828125%255Eo%25253Aid%25253Ds%2525253Ah20%25255Ehidden%25253Db%2525253A0%25255Ewidth%25253Dn%2525253A127%255Eo%25253Aid%25253Ds%2525253Ah21%25255Ehidden%25253Db%2525253A0%25255Ewidth%25253Dn%2525253A133%255Eo%25253Aid%25253Ds%2525253Ah22%25255Ehidden%25253Db%2525253A0%25255Ewidth%25253Dn%2525253A195%255Eo%25253Aid%25253Ds%2525253Ah23%25255Ehidden%25253Db%2525253A1%25255Ewidth%25253Dn%2525253A100%255Eo%25253Aid%25253Ds%2525253Ah24%25255Ehidden%25253Db%2525253A1%25255Ewidth%25253Dn%2525253A100%255Eo%25253Aid%25253Ds%2525253Ah25%25255Ehidden%25253Db%2525253A1%25255Ewidth%25253Dn%2525253A100%255Eo%25253Aid%25253Ds%2525253Ah26%25255Ehidden%25253Db%2525253A1%25255Ewidth%25253Dn%2525253A100%255Eo%25253Aid%25253Ds%2525253Ah27%25255Ehidden%25253Db%2525253A1%25255Ewidth%25253Dn%2525253A100%255Eo%25253Aid%25253Ds%2525253Ah28%25255Ehidden%25253Db%2525253A1%25255Ewidth%25253Dn%2525253A100%255Eo%25253Aid%25253Ds%2525253Ah29%25255Ehidden%25253Db%2525253A1%25255Ewidth%25253Dn%2525253A100%255Eo%25253Aid%25253Ds%2525253Ah30%25255Ehidden%25253Db%2525253A1%25255Ewidth%25253Dn%2525253A100%255Eo%25253Aid%25253Ds%2525253Ah31%25255Ehidden%25253Db%2525253A1%25255Ewidth%25253Dn%2525253A100%255Eo%25253Aid%25253Ds%2525253Ah32%25255Ehidden%25253Db%2525253A1%25255Ewidth%25253Dn%2525253A100%255Eo%25253Aid%25253Ds%2525253Ah33%25255Ehidden%25253Db%2525253A1%25255Ewidth%25253Dn%2525253A100%255Eo%25253Aid%25253Ds%2525253Ah34%25255Ehidden%25253Db%2525253A1%25255Ewidth%25253Dn%2525253A100%255Eo%25253Aid%25253Ds%2525253Ah35%25255Ehidden%25253Db%2525253A1%25255Ewidth%25253Dn%2525253A100%255Eo%25253Aid%25253Ds%2525253Ah36%25255Ehidden%25253Db%2525253A1%25255Ewidth%25253Dn%2525253A100%255Eo%25253Aid%25253Ds%2525253Ah37%25255Ehidden%25253Db%2525253A1%25255Ewidth%25253Dn%2525253A100%255Eo%25253Aid%25253Ds%2525253Ah38%25255Ehidden%25253Db%2525253A1%25255Ewidth%25253Dn%2525253A100%255Eo%25253Aid%25253Ds%2525253Ah39%25255Ehidden%25253Db%2525253A1%25255Ewidth%25253Dn%2525253A100%255Eo%25253Aid%25253Ds%2525253Ah40%25255Ehidden%25253Db%2525253A1%25255Ewidth%25253Dn%2525253A100%255Eo%25253Aid%25253Ds%2525253Ah41%25255Ehidden%25253Db%2525253A1%25255Ewidth%25253Dn%2525253A100%255Eo%25253Aid%25253Ds%2525253Ah42%25255Ehidden%25253Db%2525253A1%25255Ewidth%25253Dn%2525253A100%255Eo%25253Aid%25253Ds%2525253Ah43%25255Ehidden%25253Db%2525253A1%25255Ewidth%25253Dn%2525253A100%255Eo%25253Aid%25253Ds%2525253Ah44%25255Ehidden%25253Db%2525253A1%25255Ewidth%25253Dn%2525253A100%255Eo%25253Aid%25253Ds%2525253Ah45%25255Ehidden%25253Db%2525253A1%25255Ewidth%25253Dn%2525253A100%255Eo%25253Aid%25253Ds%2525253Ah46%25255Ehidden%25253Db%2525253A1%25255Ewidth%25253Dn%2525253A100%5EstoreState%3Do%253Asorters%253Da%25253Ao%2525253Aroot%2525253Ds%252525253Adata%2525255Eproperty%2525253Ds%252525253AmetricValue_%252525253A%252525253A_general%252525257Ctime_since_creation%2525255Edirection%2525253Ds%252525253AASC%2525255Eid%2525253Ds%252525253AmetricValue_%252525253A%252525253A_general%252525257Ctime_since_creation"
            }],
            "title": "4.  What MSSQL Databases are in the selected Instance?",
            "type": "ResourceList"
         },
         {
            "collapsed": false,
            "config": {
               "boxColumns": 3,
               "boxHeight": null,
               "labelSize": 12,
               "maxCellCount": 100,
               "metric": {
                  "mode": "resourceKind",
                  "resourceKindMetrics": [
                     {
                        "colorMethod": 1,
                        "id": "extModel13835-1",
                        "isStringMetric": false,
                        "metricKey": "active_processes|active_connections",
                        "metricName": "Active Processes|Active Connections",
                        "metricUnitId": null,
                        "resourceKindId": "resourceKind:id:1_::_",
                        "resourceKindName": "Microsoft SQL Server Database",
                        "unit": null
                     },
                     {
                        "colorMethod": 1,
                        "id": "extModel13835-2",
                        "isStringMetric": false,
                        "metricKey": "active_processes|active_transactions",
                        "metricName": "Active Processes|Active Transactions",
                        "metricUnitId": null,
                        "resourceKindId": "resourceKind:id:1_::_",
                        "resourceKindName": "Microsoft SQL Server Database",
                        "unit": null
                     },
                     {
                        "colorMethod": 1,
                        "id": "extModel13835-3",
                        "isStringMetric": false,
                        "metricKey": "performance|log_cache_read",
                        "metricName": "Performance|Log Cache Reads",
                        "metricUnitId": -1,
                        "resourceKindId": "resourceKind:id:1_::_",
                        "resourceKindName": "Microsoft SQL Server Database",
                        "unit": "Auto"
                     },
                     {
                        "colorMethod": 1,
                        "id": "extModel13835-4",
                        "isStringMetric": false,
                        "metricKey": "performance|log_pool_request",
                        "metricName": "Performance|Log Pool Requests",
                        "metricUnitId": -1,
                        "resourceKindId": "resourceKind:id:1_::_",
                        "resourceKindName": "Microsoft SQL Server Database",
                        "unit": "Auto"
                     },
                     {
                        "colorMethod": 1,
                        "id": "extModel17214-1",
                        "isStringMetric": false,
                        "metricKey": "capacity|log_size",
                        "metricName": "Capacity|Log Size",
                        "metricUnitId": -1,
                        "resourceKindId": "resourceKind:id:1_::_",
                        "resourceKindName": "Microsoft SQL Server Database",
                        "unit": "Auto"
                     },
                     {
                        "colorMethod": 1,
                        "id": "extModel17214-2",
                        "isStringMetric": false,
                        "metricKey": "disk_access|iops",
                        "metricName": "Disk Access|IOPS",
                        "metricUnitId": -1,
                        "resourceKindId": "resourceKind:id:1_::_",
                        "resourceKindName": "Microsoft SQL Server Database",
                        "unit": "Auto"
                     },
                     {
                        "colorMethod": 1,
                        "id": "extModel8435-1",
                        "isStringMetric": false,
                        "metricKey": "performance|tracked_transactions",
                        "metricName": "Performance|Tracked Transactions",
                        "metricUnitId": -1,
                        "resourceKindId": "resourceKind:id:1_::_",
                        "resourceKindName": "Microsoft SQL Server Database",
                        "unit": "Auto"
                     },
                     {
                        "colorMethod": 1,
                        "id": "extModel8435-2",
                        "isStringMetric": false,
                        "metricKey": "performance|transactions",
                        "metricName": "Performance|Transactions",
                        "metricUnitId": -1,
                        "resourceKindId": "resourceKind:id:1_::_",
                        "resourceKindName": "Microsoft SQL Server Database",
                        "unit": "Auto"
                     },
                     {
                        "colorMethod": 1,
                        "id": "extModel8435-3",
                        "isStringMetric": false,
                        "metricKey": "performance|write_transactions",
                        "metricName": "Performance|Write Transactions",
                        "metricUnitId": -1,
                        "resourceKindId": "resourceKind:id:1_::_",
                        "resourceKindName": "Microsoft SQL Server Database",
                        "unit": "Auto"
                     }
                  ],
                  "resourceMetrics": []
               },
               "mode": {"layoutMode": "fixedView"},
               "periodLength": "last7Days",
               "refreshContent": {"refreshContent": true},
               "refreshInterval": 300,
               "relationshipMode": 0,
               "resInteractionMode": null,
               "roundDecimals": null,
               "selfProvider": {"selfProvider": false},
               "showDT": {"showDT": false},
               "showMetricName": {"showMetricName": true},
               "showMetricUnit": {"showMetricUnit": true},
               "showResourceName": {"showResourceName": false},
               "showSparkline": {"showSparkline": true},
               "title": "5.  What does the selected MSSQL Database scorecard look like?",
               "valueSize": 24,
               "visualTheme": 6
            },
            "gridsterCoords": {
               "h": 5,
               "w": 6,
               "x": 7,
               "y": 12
            },
            "height": 267,
            "id": "9699b968-3e07-404d-8f3b-600249fc1712",
            "title": "5.  What does the selected MSSQL Database scorecard look like?",
            "type": "Scoreboard"
         },
         {
            "collapsed": false,
            "config": {
               "additionalColumns": [
                  {
                     "boxLabel": "OS",
                     "metricKey": "summary|guest|fullName",
                     "metricName": "Summary|Guest Operating System|Guest OS Full Name",
                     "resourceKindId": "resourceKind:id:2_::_"
                  },
                  {
                     "boxLabel": "IP",
                     "metricKey": "summary|guest|ipAddress",
                     "metricName": "Summary|Guest Operating System|Guest OS IP Address",
                     "resourceKindId": "resourceKind:id:2_::_"
                  }
               ],
               "mode": 1,
               "refreshContent": {"refreshContent": true},
               "refreshInterval": 300,
               "selectFirstRow": {"selectFirstRow": false},
               "tagFilter": {
                  "path": ["/source/kind/kind:resourceKind:id:2_::_"],
                  "value": {
                     "adapterInstance": [],
                     "adapterKind": [],
                     "bus": [],
                     "collector": [],
                     "day": [],
                     "exclaim": false,
                     "healthRange": [],
                     "kind": ["resourceKind:id:2_::_"],
                     "maintenanceSchedule": [],
                     "state": [],
                     "status": [],
                     "tag": [],
                     "tier": []
                  }
               },
               "title": "6.  What VM is the selected Instance running on?"
            },
            "gridsterCoords": {
               "h": 7,
               "w": 4,
               "x": 1,
               "y": 17
            },
            "height": 381,
            "id": "524c13da-6de8-4079-b392-30b373401f93",
            "states": [{
               "key": "permResGrid_widget_355a75be-e2ac-4916-8e10-02d87423d7d2_524c13da-6de8-4079-b392-30b373401f93",
               "value": "o%3Acolumns%3Da%253Ao%25253Aid%25253Ds%2525253Ah1%25255Ehidden%25253Db%2525253A1%25255Ewidth%25253Dn%2525253A100%255Eo%25253Aid%25253Ds%2525253Ah2%255Eo%25253Aid%25253Ds%2525253Ah3%25255Ehidden%25253Db%2525253A1%25255Ewidth%25253Dn%2525253A100%255Eo%25253Aid%25253Ds%2525253Ah4%255Eo%25253Aid%25253Ds%2525253Ah5%255Eo%25253Aid%25253Ds%2525253Ah6%255Eo%25253Aid%25253Ds%2525253Ah7%25255Ehidden%25253Db%2525253A1%25255Ewidth%25253Dn%2525253A100%255Eo%25253Aid%25253Ds%2525253Ah8%25255Ehidden%25253Db%2525253A1%25255Ewidth%25253Dn%2525253A100%255Eo%25253Aid%25253Ds%2525253Ah9%25255Ehidden%25253Db%2525253A1%25255Ewidth%25253Dn%2525253A100%255Eo%25253Aid%25253Ds%2525253Ah10%25255Ehidden%25253Db%2525253A1%25255Ewidth%25253Dn%2525253A100%255Eo%25253Aid%25253Ds%2525253Ah11%25255Ehidden%25253Db%2525253A1%25255Ewidth%25253Dn%2525253A100%255Eo%25253Aid%25253Ds%2525253Ah12%25255Ehidden%25253Db%2525253A1%25255Ewidth%25253Dn%2525253A100%255Eo%25253Aid%25253Ds%2525253Ah13%25255Ehidden%25253Db%2525253A1%25255Ewidth%25253Dn%2525253A100%255Eo%25253Aid%25253Ds%2525253Ah14%255Eo%25253Aid%25253Ds%2525253Ah15%25255Ehidden%25253Db%2525253A0%255Eo%25253Aid%25253Ds%2525253Ah16%25255Ehidden%25253Db%2525253A1%25255Ewidth%25253Dn%2525253A100%255Eo%25253Aid%25253Ds%2525253Ah17%25255Ehidden%25253Db%2525253A0%25255Ewidth%25253Dn%2525253A100%255Eo%25253Aid%25253Ds%2525253Ah18%25255Ehidden%25253Db%2525253A0%25255Ewidth%25253Dn%2525253A100%255Eo%25253Aid%25253Ds%2525253Ah19%25255Ehidden%25253Db%2525253A1%25255Ewidth%25253Dn%2525253A100%255Eo%25253Aid%25253Ds%2525253Ah20%25255Ehidden%25253Db%2525253A1%25255Ewidth%25253Dn%2525253A100%255Eo%25253Aid%25253Ds%2525253Ah21%25255Ehidden%25253Db%2525253A1%25255Ewidth%25253Dn%2525253A100%255Eo%25253Aid%25253Ds%2525253Ah22%25255Ehidden%25253Db%2525253A1%25255Ewidth%25253Dn%2525253A100%255Eo%25253Aid%25253Ds%2525253Ah23%25255Ehidden%25253Db%2525253A1%25255Ewidth%25253Dn%2525253A100%255Eo%25253Aid%25253Ds%2525253Ah24%25255Ehidden%25253Db%2525253A1%25255Ewidth%25253Dn%2525253A100%255Eo%25253Aid%25253Ds%2525253Ah25%25255Ehidden%25253Db%2525253A1%25255Ewidth%25253Dn%2525253A100%255Eo%25253Aid%25253Ds%2525253Ah26%25255Ehidden%25253Db%2525253A1%25255Ewidth%25253Dn%2525253A100%255Eo%25253Aid%25253Ds%2525253Ah27%25255Ehidden%25253Db%2525253A1%25255Ewidth%25253Dn%2525253A100%255Eo%25253Aid%25253Ds%2525253Ah28%25255Ehidden%25253Db%2525253A1%25255Ewidth%25253Dn%2525253A100%255Eo%25253Aid%25253Ds%2525253Ah29%25255Ehidden%25253Db%2525253A1%25255Ewidth%25253Dn%2525253A100%255Eo%25253Aid%25253Ds%2525253Ah30%25255Ehidden%25253Db%2525253A1%25255Ewidth%25253Dn%2525253A100%255Eo%25253Aid%25253Ds%2525253Ah31%25255Ehidden%25253Db%2525253A1%25255Ewidth%25253Dn%2525253A100%255Eo%25253Aid%25253Ds%2525253Ah32%25255Ehidden%25253Db%2525253A1%25255Ewidth%25253Dn%2525253A100%255Eo%25253Aid%25253Ds%2525253Ah33%25255Ehidden%25253Db%2525253A1%25255Ewidth%25253Dn%2525253A100%255Eo%25253Aid%25253Ds%2525253Ah34%25255Ehidden%25253Db%2525253A1%25255Ewidth%25253Dn%2525253A100%255Eo%25253Aid%25253Ds%2525253Ah35%25255Ehidden%25253Db%2525253A1%25255Ewidth%25253Dn%2525253A100%255Eo%25253Aid%25253Ds%2525253Ah36%25255Ehidden%25253Db%2525253A1%25255Ewidth%25253Dn%2525253A100%255Eo%25253Aid%25253Ds%2525253Ah37%25255Ehidden%25253Db%2525253A1%25255Ewidth%25253Dn%2525253A100%255Eo%25253Aid%25253Ds%2525253Ah38%25255Ehidden%25253Db%2525253A1%25255Ewidth%25253Dn%2525253A100%255Eo%25253Aid%25253Ds%2525253Ah39%25255Ehidden%25253Db%2525253A1%25255Ewidth%25253Dn%2525253A100%255Eo%25253Aid%25253Ds%2525253Ah40%25255Ehidden%25253Db%2525253A1%25255Ewidth%25253Dn%2525253A100%255Eo%25253Aid%25253Ds%2525253Ah41%25255Ehidden%25253Db%2525253A1%25255Ewidth%25253Dn%2525253A100%255Eo%25253Aid%25253Ds%2525253Ah42%25255Ehidden%25253Db%2525253A1%25255Ewidth%25253Dn%2525253A100%255Eo%25253Aid%25253Ds%2525253Ah43%25255Ehidden%25253Db%2525253A1%25255Ewidth%25253Dn%2525253A100%255Eo%25253Aid%25253Ds%2525253Ah44%25255Ehidden%25253Db%2525253A1%25255Ewidth%25253Dn%2525253A100%255Eo%25253Aid%25253Ds%2525253Ah45%25255Ehidden%25253Db%2525253A1%25255Ewidth%25253Dn%2525253A100%255Eo%25253Aid%25253Ds%2525253Ah46%25255Ehidden%25253Db%2525253A1%25255Ewidth%25253Dn%2525253A100"
            }],
            "title": "6.  What VM is the selected Instance running on?",
            "type": "ResourceList"
         },
         {
            "collapsed": false,
            "config": {
               "customFilter": {
                  "excludedResources": null,
                  "filter": [],
                  "includedResources": null
               },
               "depth": "0,4",
               "filterMode": "tagPicker",
               "refreshContent": {"refreshContent": true},
               "refreshInterval": 300,
               "resourceId": null,
               "resourceName": null,
               "selfProvider": {"selfProvider": false},
               "tagFilter": null,
               "title": "3. Health of objects related to the selected Instance?",
               "traversalSpecId": ""
            },
            "gridsterCoords": {
               "h": 6,
               "w": 12,
               "x": 1,
               "y": 6
            },
            "height": 324,
            "id": "486c7db0-59fd-4e81-ae5f-12ebcf92ee6e",
            "states": [
               {
                  "key": "perm_toolbarVisible_widget_355a75be-e2ac-4916-8e10-02d87423d7d2_486c7db0-59fd-4e81-ae5f-12ebcf92ee6e",
                  "value": "b%3A0"
               },
               {
                  "key": "perm_viewerType_widget_355a75be-e2ac-4916-8e10-02d87423d7d2_486c7db0-59fd-4e81-ae5f-12ebcf92ee6e",
                  "value": "s%3ArelationshipTree"
               },
               {
                  "key": "perm_ResourceRelationshipTree_widget_355a75be-e2ac-4916-8e10-02d87423d7d2_486c7db0-59fd-4e81-ae5f-12ebcf92ee6e",
                  "value": "o%3A"
               }
            ],
            "title": "3. Health of objects related to the selected Instance?",
            "type": "ResourceRelationshipAdvanced"
         },
         {
            "collapsed": false,
            "config": {
               "customFilter": {
                  "excludedResources": null,
                  "filter": [],
                  "includedResources": null
               },
               "depth": "3,3",
               "filterMode": "tagPicker",
               "refreshContent": {"refreshContent": true},
               "refreshInterval": 300,
               "resourceId": null,
               "resourceName": null,
               "selfProvider": {"selfProvider": false},
               "tagFilter": null,
               "title": "7.  Health of objects related to the selected VM",
               "traversalSpecId": ""
            },
            "gridsterCoords": {
               "h": 7,
               "w": 8,
               "x": 5,
               "y": 17
            },
            "height": 381,
            "id": "78b3bdc0-5dac-41e3-8520-a520db96e873",
            "title": "7.  Health of objects related to the selected VM",
            "type": "ResourceRelationshipAdvanced"
         }
      ]
   }],
   "entries": {"resourceKind": [
      {
         "adapterKindKey": "VMWARE",
         "internalId": "resourceKind:id:2_::_",
         "resourceKindKey": "VirtualMachine"
      },
      {
         "adapterKindKey": "SqlServerAdapter",
         "internalId": "resourceKind:id:0_::_",
         "resourceKindKey": "SqlServer"
      },
      {
         "adapterKindKey": "SqlServerAdapter",
         "internalId": "resourceKind:id:1_::_",
         "resourceKindKey": "SqlDatabase"
      }
   ]},
   "uuid": "46b608e0-5fa1-4195-88b5-9054ec295fae"
}